mw4/__init__.py
mw4/__main__.py
mw4/assets/__init__.py
mw4/assets/assetsData.py
mw4/base/__init__.py
mw4/base/alpacaClass.py
mw4/base/ascomClass.py
mw4/base/driverDataClass.py
mw4/base/ethernet.py
mw4/base/indiClass.py
mw4/base/loggerMW.py
mw4/base/ninaClass.py
mw4/base/packageConfig.py
mw4/base/sgproClass.py
mw4/base/signalsDevices.py
mw4/base/tpool.py
mw4/base/transform.py
mw4/cli.py
mw4/gui/__init__.py
mw4/gui/extWindows/__init__.py
mw4/gui/extWindows/analyseW.py
mw4/gui/extWindows/bigPopupW.py
mw4/gui/extWindows/devicePopupW.py
mw4/gui/extWindows/downloadPopupW.py
mw4/gui/extWindows/hemisphere/__init__.py
mw4/gui/extWindows/hemisphere/hemisphereDraw.py
mw4/gui/extWindows/hemisphere/hemisphereW.py
mw4/gui/extWindows/hemisphere/horizonDraw.py
mw4/gui/extWindows/image/__init__.py
mw4/gui/extWindows/image/imageSignals.py
mw4/gui/extWindows/image/imageTabs.py
mw4/gui/extWindows/image/imageW.py
mw4/gui/extWindows/keypadW.py
mw4/gui/extWindows/measureW.py
mw4/gui/extWindows/messageW.py
mw4/gui/extWindows/satelliteW.py
mw4/gui/extWindows/simulator/__init__.py
mw4/gui/extWindows/simulator/buildPoints.py
mw4/gui/extWindows/simulator/dome.py
mw4/gui/extWindows/simulator/horizon.py
mw4/gui/extWindows/simulator/laser.py
mw4/gui/extWindows/simulator/light.py
mw4/gui/extWindows/simulator/materials.py
mw4/gui/extWindows/simulator/pointer.py
mw4/gui/extWindows/simulator/simulatorW.py
mw4/gui/extWindows/simulator/telescope.py
mw4/gui/extWindows/simulator/tools.py
mw4/gui/extWindows/simulator/world.py
mw4/gui/extWindows/uploadPopupW.py
mw4/gui/extWindows/video/__init__.py
mw4/gui/extWindows/video/videoBase.py
mw4/gui/extWindows/video/videoW.py
mw4/gui/mainWaddon/__init__.py
mw4/gui/mainWaddon/astroObjects.py
mw4/gui/mainWaddon/satData.py
mw4/gui/mainWaddon/tabAlmanac.py
mw4/gui/mainWaddon/tabAnalysis.py
mw4/gui/mainWaddon/tabAsteroid.py
mw4/gui/mainWaddon/tabComet.py
mw4/gui/mainWaddon/tabEnviron_Seeing.py
mw4/gui/mainWaddon/tabEnviron_Weather.py
mountwizzard4-4.0.0a38.dist-info/WHEEL
mountwizzard4-4.0.0a38.dist-info/entry_points.txt
mountwizzard4-4.0.0a38.dist-info/METADATA
mountwizzard4-4.0.0a38.dist-info/RECORD
