Metadata-Version: 2.4
Name: mountwizzard4
Version: 4.0.0a38
Summary: Tool for managing 10micron mounts
Keywords: 6.9.3
Author: Michael Wuertenberger
Author-email: Michael Wuertenberger <michael@wuertenberger.org>
License-Expression: Apache-2.0
Classifier: Development Status :: 5 - Production/Stable
Classifier: Environment :: MacOS X
Classifier: Environment :: Other Environment
Classifier: Programming Language :: Python :: 3.11
Classifier: Programming Language :: Python :: 3.12
Classifier: Programming Language :: Python :: 3.13
Classifier: Programming Language :: Python :: 3 :: Only
Classifier: Programming Language :: Python :: Implementation
Classifier: Operating System :: MacOS :: MacOS X
Classifier: Operating System :: Microsoft :: Windows :: Windows 10
Classifier: Operating System :: Microsoft :: Windows :: Windows 11
Classifier: Operating System :: POSIX :: Linux
Classifier: Intended Audience :: Developers
Classifier: Intended Audience :: Education
Classifier: Intended Audience :: Science/Research
Classifier: Topic :: Utilities
Classifier: Topic :: Scientific/Engineering :: Astronomy
Classifier: Natural Language :: English
Classifier: Natural Language :: German
Classifier: Topic :: Documentation :: Sphinx
Requires-Dist: numpy==2.2.6
Requires-Dist: opencv-python-headless==4.12.0.88
Requires-Dist: scipy==1.16.2
Requires-Dist: astropy==7.1.1
Requires-Dist: pyerfa==2.0.1.5
Requires-Dist: astroquery==0.4.11
Requires-Dist: sep==1.4.1
Requires-Dist: pyqtgraph==0.13.7
Requires-Dist: qimage2ndarray==1.10.0
Requires-Dist: skyfield==1.53
Requires-Dist: sgp4==2.25
Requires-Dist: requests==2.32.5
Requires-Dist: requests-toolbelt==1.0.0
Requires-Dist: importlib-metadata==8.7.0
Requires-Dist: python-dateutil==2.9.0.post0
Requires-Dist: wakeonlan==3.1.0
Requires-Dist: pybase64==1.4.2
Requires-Dist: websocket-client==1.9.0
Requires-Dist: hidapi==0.14.0.post4
Requires-Dist: range-key-dict==1.1.0
Requires-Dist: ndicts==0.3.0
Requires-Dist: packaging==25.0
Requires-Dist: lz4==4.4.4
Requires-Dist: xisf==0.9.5
Requires-Dist: pyside6==6.10.0
Requires-Dist: pywin32==311 ; sys_platform == 'win32'
Requires-Python: >=3.11, <3.14
Project-URL: BugTracker, https://github.com/mworion/mountwizzard4/issues
Project-URL: Channel, https://www.youtube.com/user/orion49m/featured
Project-URL: Discussions, https://github.com/mworion/MountWizzard4/discussions
Project-URL: Documentation, https://mworion.github.io/MountWizzard4
Project-URL: Forum, https://www.10micron.eu/forum/
Project-URL: Source, https://github.com/mworion/mountwizzard4
